s3sql/cli.py
s3sql/test_cli.py
s3sql-0.0.6.dist-info/entry_points.txt
s3sql-0.0.6.dist-info/METADATA
s3sql-0.0.6.dist-info/WHEEL
s3sql-0.0.6.dist-info/RECORD
