Metadata-Version: 2.3
Name: s3sql
Version: 0.0.6
Summary: A simple CLI to query cloud storage objects with SQL.
Author: Ian Fogelman
Author-email: IanFogelman@gmail.com
Requires-Python: >=3.9,<4.0
Classifier: Programming Language :: Python :: 3
Classifier: Programming Language :: Python :: 3.9
Classifier: Programming Language :: Python :: 3.10
Classifier: Programming Language :: Python :: 3.11
Classifier: Programming Language :: Python :: 3.12
Classifier: Programming Language :: Python :: 3.13
Requires-Dist: aiobotocore (==2.13.0)
Requires-Dist: boto3 (==1.34.70)
Requires-Dist: botocore (==1.34.70)
Requires-Dist: bottleneck (>=1.3.6)
Requires-Dist: click (>=8.1.3,<9.0.0)
Requires-Dist: duckdb (>=1.0.0,<2.0.0)
Requires-Dist: fsspec (==2024.6.0)
Requires-Dist: pandas (>=2.2.0,<3.0.0)
Requires-Dist: requests (>=2.32.3,<3.0.0)
Requires-Dist: s3fs (==2024.6.0)
Requires-Dist: tabulate (>=0.9.0,<0.10.0)
